mo_cmd/__init__.py
mo_cmd/cmd.py
mo_cmd-0.1.4.dist-info/METADATA
mo_cmd-0.1.4.dist-info/WHEEL
mo_cmd-0.1.4.dist-info/entry_points.txt
mo_cmd-0.1.4.dist-info/top_level.txt
mo_cmd-0.1.4.dist-info/RECORD
