Metadata-Version: 2.1
Name: mo_cmd
Version: 0.1.4
Summary: PDM add, sub, div calculate package
Author-email: oddsummer56 <oddsummer56@gmail.com>
License: MIT
Requires-Python: >=3.9
Requires-Dist: mo-plus >=0.1.0
Requires-Dist: mo-minus >=0.1.0
Requires-Dist: mo-divide >=0.1.0
